chatlogger_core-0.1.1.dist-info/METADATA
chatlogger_core-0.1.1.dist-info/WHEEL
chatlogger_core/__init__.py
chatlogger_core/chatlogger_core.cp310-win_amd64.pyd
chatlogger_core-0.1.1.dist-info/RECORD
